cporter
