Metadata-Version: 1.1
Name: cporter
Version: 0.2.0
Summary: Cporter, sync files between Cloud Storage[Dropbox, UpYun,...].
Home-page: https://github.com/WhiteWorld/cporter
Author: whiteworld
Author-email: ljq258@gmail.com
License: MIT
Keywords: Dropbox UpYun sync
Platform: UNKNOWN
Classifier: Development Status :: 4 - Beta
Classifier: Intended Audience :: Developers
Classifier: Topic :: Software Development :: Build Tools
Classifier: License :: OSI Approved :: MIT License
Classifier: Programming Language :: Python :: 2
Classifier: Programming Language :: Python :: 2.6
Classifier: Programming Language :: Python :: 2.7
